optionpy/__init__.py
optionpy/__version__.py
optionpy/greeks.py
optionpy/iv.py
optionpy/option.py
optionpy/price.py
optionpy/sim.py
optionpy/stats.py
optionpy/.info/CHANGELOG
optionpy/.version/version.dat
optionpy/auxiliary/__init__.py
optionpy/auxiliary/auxiliary.py
optionpy/auxiliary/utility.py
optionpy-0.0.2.dist-info/LICENSE
optionpy-0.0.2.dist-info/METADATA
optionpy-0.0.2.dist-info/WHEEL
optionpy-0.0.2.dist-info/top_level.txt
optionpy-0.0.2.dist-info/RECORD
