Metadata-Version: 2.1
Name: optionpy
Version: 0.0.2
Summary: Calculation of option price, greeks and implied volatility
Home-page: https://github.com/ibaris/optionpy
Author: Ismail Baris
Author-email: i.baris@outlook.de
Maintainer: Ismail Baris
License: UNKNOWN
Platform: UNKNOWN
Classifier: Intended Audience :: Science/Research
Classifier: Intended Audience :: Developers
Classifier: Intended Audience :: Education
Classifier: Intended Audience :: End Users/Desktop
Classifier: Programming Language :: Python :: 3.7
Classifier: Operating System :: Microsoft
License-File: LICENSE
